frida_mcp/cli.py
frida_mcp-0.1.1.dist-info/METADATA
frida_mcp-0.1.1.dist-info/WHEEL
frida_mcp-0.1.1.dist-info/entry_points.txt
frida_mcp-0.1.1.dist-info/RECORD
