Metadata-Version: 2.4
Name: frida-mcp
Version: 0.1.1
Summary: Model Context Protocol implementation for Frida
License: MIT
Requires-Python: >=3.8
Requires-Dist: frida>=16.0.0
Requires-Dist: mcp>=1.5.0
Provides-Extra: dev
Requires-Dist: black; extra == 'dev'
Requires-Dist: mypy; extra == 'dev'
